Cryptsy.py
setup.py
Cryptsy.egg-info/PKG-INFO
Cryptsy.egg-info/SOURCES.txt
Cryptsy.egg-info/dependency_links.txt
Cryptsy.egg-info/not-zip-safe
Cryptsy.egg-info/top_level.txt