Metadata-Version: 1.1
Name: Cryptsy
Version: 0.2
Summary: A python wrapper for the Cryptsy API.
Home-page: https://github.com/jaapz/CryptsyPythonAPI
Author: Jaap Broekhuizen <jaapz.b@gmail.com>, Matt Joseph Smith <matt.joseph.smith@gmail.com>
Author-email: UNKNOWN
License: GNU GPL2
Platform: any
Classifier: Intended Audience :: Developers
Classifier: License :: OSI Approved :: GNU General Public License v2 (GPLv2)
Classifier: Operating System :: OS Independent
Classifier: Programming Language :: Python
Classifier: Topic :: Internet :: WWW/HTTP :: Dynamic Content
Classifier: Topic :: Software Development :: Libraries :: Python Modules
